llme/__init__.py
llme/__main__.py
llme/_version.py
llme/config.toml
llme/main.py
llme_cli-0.1.4.dist-info/licenses/LICENSE
llme_cli-0.1.4.dist-info/METADATA
llme_cli-0.1.4.dist-info/WHEEL
llme_cli-0.1.4.dist-info/entry_points.txt
llme_cli-0.1.4.dist-info/top_level.txt
llme_cli-0.1.4.dist-info/RECORD
