Metadata-Version: 2.4
Name: llme-cli
Version: 0.1.4
Summary: A command-line interface for language models
Author-email: Jean Privat <jean@pryen.org>
License-Expression: GPL-3.0-or-later
Project-URL: Repository, https://github.com/privat/llme
Classifier: Programming Language :: Python :: 3
Classifier: Operating System :: OS Independent
Requires-Python: >=3.7
License-File: LICENSE
Requires-Dist: requests
Requires-Dist: termcolor
Requires-Dist: prompt-toolkit
Requires-Dist: python-magic
Dynamic: license-file
